analyzefamily/__init__.py
analyzefamily/ancerstors_climb.py
analyzefamily/matcher_geni_profile.py
analyzefamily/process_for_matches.py
analyzefamily/quality_check.py
analyzefamily/sync_profile.py
geniApp/__init__.py
geniApp/data_storing.py
gui_genitools/__init__.py
gui_genitools/mainApp.py
gui_genitools/messages_gui.py
gui_genitools/gui_frame/__init__.py
gui_genitools/gui_frame/geni_fs_import.py
gui_genitools/gui_frame/geni_key_frame.py
gui_genitools/gui_frame/main_frame.py
messages/__init__.py
messages/genitools_messages.py
messages/parser_messages.py
messages/pyFS_messages.py
messages/pyGenealogymessages.py
messages/py_rootsmagic_messages.py
messages/pygenanalyzer_messages.py
messages/pygeni_messages.py
parser_input/__init__.py
parser_input/reader_input.py
pyFS/__init__.py
pyFS/pyfs_open_xlsx.py
pyGedcom/__init__.py
pyGedcom/gedcom_database.py
pyGedcom/gedcom_family.py
pyGedcom/gedcom_profile.py
pyGenealogy/__init__.py
pyGenealogy/common_database.py
pyGenealogy/common_event.py
pyGenealogy/common_family.py
pyGenealogy/common_profile.py
pyGenealogy/gen_utils.py
pyGenealogy/generic_functions.py
pyGeni/__init__.py
pyGeni/data_models.py
pyGeni/geni2gedcom.py
pyGeni/geniapi_common.py
pyGeni/immediate_family.py
pyGeni/interface_geni_database.py
pyGeni/profile.py
pyGeni/union.py
pyGeni/__pycache__/__init__.cpython-36.pyc
pyGeni/__pycache__/profile.cpython-36.pyc
pyRegisters/__init__.py
pyRegisters/pyCommonRegisters.py
pyRegisters/pyabc.py
pyRegisters/pycementry_valencia.py
pyRegisters/pyelnortedecastilla.py
pyRegisters/pyesquelas.py
pyRegisters/pygenanalyzer.py
pyRegisters/pylavanguardia.py
pyRegisters/pyrememori.py
pyRegisters/pyvocento.py
pyRootsMagic/__init__.py
pyRootsMagic/pyrm_database.py
pyRootsMagic/rootsmagic_family.py
pyRootsMagic/rootsmagic_profile.py
tests/FIXTURES.py
tests/__init__.py
tests/myTests.py
tests/testAncestorsClimb.py
tests/testFSexcel.py
tests/testFSexcel_creationGeni.py
tests/testFSexcel_wrongGeni.py
tests/testGUI.py
tests/testGeniApp.py
pyGenealogicalTools-1.0.2.dist-info/LICENSE
pyGenealogicalTools-1.0.2.dist-info/METADATA
pyGenealogicalTools-1.0.2.dist-info/WHEEL
pyGenealogicalTools-1.0.2.dist-info/top_level.txt
pyGenealogicalTools-1.0.2.dist-info/RECORD
