Metadata-Version: 2.1
Name: pyGenealogicalTools
Version: 1.0.2
Summary: Genealogical tools
Home-page: https://github.com/Thimxx/pyGenealogical-Tools
Author: Val
License: GPL-3.0
Platform: UNKNOWN
Classifier: Programming Language :: Python :: 3
Classifier: License :: OSI Approved :: GNU General Public License v3 (GPLv3)
Classifier: Operating System :: OS Independent
Classifier: Topic :: Sociology :: Genealogy
Requires-Dist: requests
Requires-Dist: openpyxl
Requires-Dist: pyexcel
Requires-Dist: pyexcel-xls
Requires-Dist: python-Levenshtein
Requires-Dist: pyexcel-xlsx
Requires-Dist: metaphone
Requires-Dist: langdetect
Requires-Dist: mapbox
Requires-Dist: geotext
Requires-Dist: python-dateutil
